lib2/__init__.py
lib2/__main__.py
lib2/app.py
lib2/cli.py
e5fda7ba_d2a1_11e9_96d1_7c5cf84ffe8e-0.1.0.dist-info/entry_points.txt
e5fda7ba_d2a1_11e9_96d1_7c5cf84ffe8e-0.1.0.dist-info/LICENSE
e5fda7ba_d2a1_11e9_96d1_7c5cf84ffe8e-0.1.0.dist-info/WHEEL
e5fda7ba_d2a1_11e9_96d1_7c5cf84ffe8e-0.1.0.dist-info/METADATA
e5fda7ba_d2a1_11e9_96d1_7c5cf84ffe8e-0.1.0.dist-info/RECORD
